{"data":{"site":{"siteMetadata":{"title":"Computer Science and Software Engineering","author":"Assignment 04"}},"markdownRemark":{"id":"d44e47b4-0ea3-5355-8032-04f05b999363","excerpt":"Mijn naam is De Coene Bruno, student aan Arteveldehogeschool.","html":"<p>Mijn naam is De Coene Bruno, student aan Arteveldehogeschool.</p>\n<p><img src=\"./profile-2.png\" alt=\"Image by Bruno De Coene\"></p>","fields":{"readingTime":{"text":"1 min read"}},"frontmatter":{"title":"Over auteur","date":"14 April, 2018"}}},"pageContext":{"isCreatedByStatefulCreatePages":false,"slug":"/over-auteur/","previous":null,"next":{"fields":{"slug":"/text-headings/"},"frontmatter":{"title":"Just text and links"}}}}